umpyre/__init__.py
umpyre/cli.py
umpyre/config.py
umpyre/python_code_stats.py
umpyre/schema.py
umpyre/collectors/__init__.py
umpyre/collectors/base.py
umpyre/collectors/coverage_collector.py
umpyre/collectors/umpyre_collector.py
umpyre/collectors/wily_collector.py
umpyre/collectors/workflow_status.py
umpyre/storage/__init__.py
umpyre/storage/formats.py
umpyre/storage/git_branch.py
umpyre/storage/query_utils.py
umpyre-0.1.1.dist-info/METADATA
umpyre-0.1.1.dist-info/WHEEL
umpyre-0.1.1.dist-info/entry_points.txt
umpyre-0.1.1.dist-info/licenses/LICENSE
umpyre-0.1.1.dist-info/RECORD
