Metadata-Version: 2.4
Name: umpyre
Version: 0.1.1
Summary: Code analysis and quality metrics tracking system for CI/CD
Project-URL: Homepage, https://github.com/i2mint/umpyre
License: Apache-2.0
License-File: LICENSE
Keywords: CI/CD,code analysis,metrics,quality tracking
Requires-Python: >=3.10
Requires-Dist: dol
Requires-Dist: pandas
Requires-Dist: pyyaml
Requires-Dist: requests
